AUTHORS.rst
CONTRIBUTING.rst
HISTORY.rst
LICENSE
MANIFEST.in
README.rst
setup.py
pyover/__init__.py
pyover/pyover.py
pyover.egg-info/PKG-INFO
pyover.egg-info/SOURCES.txt
pyover.egg-info/dependency_links.txt
pyover.egg-info/not-zip-safe
pyover.egg-info/requires.txt
pyover.egg-info/top_level.txt