Metadata-Version: 1.1
Name: pyover
Version: 0.1.0
Summary: Python module to interface with pushover.
Home-page: https://github.com/ainmosni/pyover
Author: Daniël Franke
Author-email: daniel@ams-sec.org
License: BSD
Keywords: pyover
Platform: UNKNOWN
Classifier: Development Status :: 2 - Pre-Alpha
Classifier: Intended Audience :: Developers
Classifier: License :: OSI Approved :: BSD License
Classifier: Natural Language :: English
Classifier: Programming Language :: Python :: 2
Classifier: Programming Language :: Python :: 2.7
Classifier: Programming Language :: Python :: 3
Classifier: Programming Language :: Python :: 3.3
